{
  "openapi": "3.1.0",
  "info": {
    "title": "ChromaDB API",
    "description": "This is OpenAPI schema for ChromaDB API.",
    "version": "0.1.0",
    "x-logo": {
      "url": "https://www.trychroma.com/chroma-logo.png"
    }
  },
  "servers": [
    {
      "url": "http://localhost:8000"
    }
  ],
  "paths": {
    "/api/v1": {
      "get": {
        "summary": "Root",
        "operationId": "root",
        "responses": {
          "200": {
            "description": "Successful Response",
            "content": {
              "application/json": {
                "schema": {
                  "additionalProperties": {
                    "type": "integer"
                  },
                  "type": "object",
                  "title": "Response Root Api V1 Get"
                }
              }
            }
          }
        }
      }
    },
    "/api/v1/reset": {
      "post": {
        "summary": "Reset",
        "operationId": "reset",
        "responses": {
          "200": {
            "description": "Successful Response",
            "content": {
              "application/json": {
                "schema": {
                  "type": "boolean",
                  "title": "Response Reset Api V1 Reset Post"
                }
              }
            }
          }
        }
      }
    },
    "/api/v1/version": {
      "get": {
        "summary": "Version",
        "operationId": "version",
        "responses": {
          "200": {
            "description": "Successful Response",
            "content": {
              "application/json": {
                "schema": {
                  "type": "string",
                  "title": "Response Version Api V1 Version Get"
                }
              }
            }
          }
        }
      }
    },
    "/api/v1/heartbeat": {
      "get": {
        "summary": "Heartbeat",
        "operationId": "heartbeat",
        "responses": {
          "200": {
            "description": "Successful Response",
            "content": {
              "application/json": {
                "schema": {
                  "additionalProperties": {
                    "type": "integer"
                  },
                  "type": "object",
                  "title": "Response Heartbeat Api V1 Heartbeat Get"
                }
              }
            }
          }
        }
      }
    },
    "/api/v1/pre-flight-checks": {
      "get": {
        "summary": "Pre Flight Checks",
        "operationId": "pre_flight_checks",
        "responses": {
          "200": {
            "description": "Successful Response",
            "content": {
              "application/json": {
                "schema": {
                  "type": "object",
                  "title": "Response Pre Flight Checks Api V1 Pre Flight Checks Get"
                }
              }
            }
          }
        }
      }
    },
    "/api/v1/databases": {
      "post": {
        "summary": "Create Database",
        "operationId": "create_database",
        "parameters": [
          {
            "name": "tenant",
            "in": "query",
            "required": false,
            "schema": {
              "type": "string",
              "default": "default_tenant",
              "title": "Tenant"
            }
          }
        ],
        "requestBody": {
          "required": true,
          "content": {
            "application/json": {
              "schema": {
                "$ref": "#/components/schemas/CreateDatabase"
              }
            }
          }
        },
        "responses": {
          "200": {
            "description": "Successful Response",
            "content": {
              "application/json": {
                "schema": {
                  "type": "array",
                  "items": {
                    "$ref": "#/components/schemas/DatabaseType"
                  }
                }
              }
            }
          },
          "422": {
            "description": "Validation Error",
            "content": {
              "application/json": {
                "schema": {
                  "$ref": "#/components/schemas/HTTPValidationError"
                }
              }
            }
          }
        }
      }
    },
    "/api/v1/databases/{database}": {
      "get": {
        "summary": "Get Database",
        "operationId": "get_database",
        "parameters": [
          {
            "name": "database",
            "in": "path",
            "required": true,
            "schema": {
              "type": "string",
              "title": "Database"
            }
          },
          {
            "name": "tenant",
            "in": "query",
            "required": false,
            "schema": {
              "type": "string",
              "default": "default_tenant",
              "title": "Tenant"
            }
          }
        ],
        "responses": {
          "200": {
            "description": "Successful Response",
            "content": {
              "application/json": {
                "schema": {
                  "$ref": "#/components/schemas/DatabaseType"
                }
              }
            }
          },
          "422": {
            "description": "Validation Error",
            "content": {
              "application/json": {
                "schema": {
                  "$ref": "#/components/schemas/HTTPValidationError"
                }
              }
            }
          }
        }
      }
    },
    "/api/v1/tenants": {
      "post": {
        "summary": "Create Tenant",
        "operationId": "create_tenant",
        "requestBody": {
          "content": {
            "application/json": {
              "schema": {
                "$ref": "#/components/schemas/CreateTenant"
              }
            }
          },
          "required": true
        },
        "responses": {
          "200": {
            "description": "Successful Response",
            "content": {
              "application/json": {
                "schema": {
                  "type": "array",
                  "items": {
                    "$ref": "#/components/schemas/TenantType"
                  }
                }
              }
            }
          },
          "422": {
            "description": "Validation Error",
            "content": {
              "application/json": {
                "schema": {
                  "$ref": "#/components/schemas/HTTPValidationError"
                }
              }
            }
          }
        }
      }
    },
    "/api/v1/tenants/{tenant}": {
      "get": {
        "summary": "Get Tenant",
        "operationId": "get_tenant",
        "parameters": [
          {
            "name": "tenant",
            "in": "path",
            "required": true,
            "schema": {
              "type": "string",
              "title": "Tenant"
            }
          }
        ],
        "responses": {
          "200": {
            "description": "Successful Response",
            "content": {
              "application/json": {
                "schema": {
                  "$ref": "#/components/schemas/TenantType"
                }
              }
            }
          },
          "422": {
            "description": "Validation Error",
            "content": {
              "application/json": {
                "schema": {
                  "$ref": "#/components/schemas/HTTPValidationError"
                }
              }
            }
          }
        }
      }
    },
    "/api/v1/collections": {
      "get": {
        "summary": "List Collections",
        "operationId": "list_collections",
        "parameters": [
          {
            "name": "tenant",
            "in": "query",
            "required": false,
            "schema": {
              "type": "string",
              "default": "default_tenant",
              "title": "Tenant"
            }
          },
          {
            "name": "database",
            "in": "query",
            "required": false,
            "schema": {
              "type": "string",
              "default": "default_database",
              "title": "Database"
            }
          }
        ],
        "responses": {
          "200": {
            "description": "Successful Response",
            "content": {
              "application/json": {
                "schema": {
                  "title": "Collections",
                  "type": "array",
                  "items": {
                    "$ref": "#/components/schemas/CollectionType"
                  }
                }
              }
            }
          },
          "422": {
            "description": "Validation Error",
            "content": {
              "application/json": {
                "schema": {
                  "$ref": "#/components/schemas/HTTPValidationError"
                }
              }
            }
          }
        }
      },
      "post": {
        "summary": "Create Collection",
        "operationId": "create_collection",
        "parameters": [
          {
            "name": "tenant",
            "in": "query",
            "required": false,
            "schema": {
              "type": "string",
              "default": "default_tenant",
              "title": "Tenant"
            }
          },
          {
            "name": "database",
            "in": "query",
            "required": false,
            "schema": {
              "type": "string",
              "default": "default_database",
              "title": "Database"
            }
          }
        ],
        "requestBody": {
          "required": true,
          "content": {
            "application/json": {
              "schema": {
                "$ref": "#/components/schemas/CreateCollection"
              }
            }
          }
        },
        "responses": {
          "200": {
            "description": "Successful Response",
            "content": {
              "application/json": {
                "schema": {
                  "$ref": "#/components/schemas/CollectionType"
                }
              }
            }
          },
          "422": {
            "description": "Validation Error",
            "content": {
              "application/json": {
                "schema": {
                  "$ref": "#/components/schemas/HTTPValidationError"
                }
              }
            }
          }
        }
      }
    },
    "/api/v1/collections/{collection_id}/add": {
      "post": {
        "summary": "Add",
        "operationId": "add",
        "parameters": [
          {
            "name": "collection_id",
            "in": "path",
            "required": true,
            "schema": {
              "type": "string",
              "title": "Collection Id"
            }
          }
        ],
        "requestBody": {
          "required": true,
          "content": {
            "application/json": {
              "schema": {
                "$ref": "#/components/schemas/AddEmbedding"
              }
            }
          }
        },
        "responses": {
          "201": {
            "description": "Successful Response",
            "content": {
              "application/json": {
                "schema": {
                  "type": "object"
                }
              }
            }
          },
          "422": {
            "description": "Validation Error",
            "content": {
              "application/json": {
                "schema": {
                  "$ref": "#/components/schemas/HTTPValidationError"
                }
              }
            }
          }
        }
      }
    },
    "/api/v1/collections/{collection_id}/update": {
      "post": {
        "summary": "Update",
        "operationId": "update",
        "parameters": [
          {
            "name": "collection_id",
            "in": "path",
            "required": true,
            "schema": {
              "type": "string",
              "title": "Collection Id"
            }
          }
        ],
        "requestBody": {
          "required": true,
          "content": {
            "application/json": {
              "schema": {
                "$ref": "#/components/schemas/UpdateEmbedding"
              }
            }
          }
        },
        "responses": {
          "200": {
            "description": "Successful Response",
            "content": {
              "application/json": {
                "schema": {
                  "type": "object"
                }
              }
            }
          },
          "422": {
            "description": "Validation Error",
            "content": {
              "application/json": {
                "schema": {
                  "$ref": "#/components/schemas/HTTPValidationError"
                }
              }
            }
          }
        }
      }
    },
    "/api/v1/collections/{collection_id}/upsert": {
      "post": {
        "summary": "Upsert",
        "operationId": "upsert",
        "parameters": [
          {
            "name": "collection_id",
            "in": "path",
            "required": true,
            "schema": {
              "type": "string",
              "title": "Collection Id"
            }
          }
        ],
        "requestBody": {
          "required": true,
          "content": {
            "application/json": {
              "schema": {
                "$ref": "#/components/schemas/AddEmbedding"
              }
            }
          }
        },
        "responses": {
          "200": {
            "description": "Successful Response",
            "content": {
              "application/json": {
                "schema": {
                  "type": "object"
                }
              }
            }
          },
          "422": {
            "description": "Validation Error",
            "content": {
              "application/json": {
                "schema": {
                  "$ref": "#/components/schemas/HTTPValidationError"
                }
              }
            }
          }
        }
      }
    },
    "/api/v1/collections/{collection_id}/get": {
      "post": {
        "summary": "Get",
        "operationId": "get",
        "parameters": [
          {
            "name": "collection_id",
            "in": "path",
            "required": true,
            "schema": {
              "type": "string",
              "title": "Collection Id"
            }
          }
        ],
        "requestBody": {
          "required": true,
          "content": {
            "application/json": {
              "schema": {
                "$ref": "#/components/schemas/GetEmbedding"
              }
            }
          }
        },
        "responses": {
          "200": {
            "description": "Successful Response",
            "content": {
              "application/json": {
                "schema": {
                  "$ref": "#/components/schemas/GetResponse"
                }
              }
            }
          },
          "422": {
            "description": "Validation Error",
            "content": {
              "application/json": {
                "schema": {
                  "$ref": "#/components/schemas/HTTPValidationError"
                }
              }
            }
          }
        }
      }
    },
    "/api/v1/collections/{collection_id}/delete": {
      "post": {
        "summary": "Delete",
        "operationId": "delete",
        "parameters": [
          {
            "name": "collection_id",
            "in": "path",
            "required": true,
            "schema": {
              "type": "string",
              "title": "Collection Id"
            }
          }
        ],
        "requestBody": {
          "required": true,
          "content": {
            "application/json": {
              "schema": {
                "$ref": "#/components/schemas/DeleteEmbedding"
              }
            }
          }
        },
        "responses": {
          "200": {
            "description": "Successful Response",
            "content": {
              "application/json": {
                "schema": {
                  "items": {
                    "type": "string",
                    "format": "uuid"
                  },
                  "type": "array"
                }
              }
            }
          },
          "422": {
            "description": "Validation Error",
            "content": {
              "application/json": {
                "schema": {
                  "$ref": "#/components/schemas/HTTPValidationError"
                }
              }
            }
          }
        }
      }
    },
    "/api/v1/collections/{collection_id}/count": {
      "get": {
        "summary": "Count",
        "operationId": "count",
        "parameters": [
          {
            "name": "collection_id",
            "in": "path",
            "required": true,
            "schema": {
              "type": "string",
              "title": "Collection Id"
            }
          }
        ],
        "responses": {
          "200": {
            "description": "Successful Response",
            "content": {
              "application/json": {
                "schema": {
                  "type": "integer"
                }
              }
            }
          },
          "422": {
            "description": "Validation Error",
            "content": {
              "application/json": {
                "schema": {
                  "$ref": "#/components/schemas/HTTPValidationError"
                }
              }
            }
          }
        }
      }
    },
    "/api/v1/collections/{collection_id}/query": {
      "post": {
        "summary": "Get Nearest Neighbors",
        "operationId": "get_nearest_neighbors",
        "parameters": [
          {
            "name": "collection_id",
            "in": "path",
            "required": true,
            "schema": {
              "type": "string",
              "title": "Collection Id"
            }
          }
        ],
        "requestBody": {
          "required": true,
          "content": {
            "application/json": {
              "schema": {
                "$ref": "#/components/schemas/QueryEmbedding"
              }
            }
          }
        },
        "responses": {
          "200": {
            "description": "Successful Response",
            "content": {
              "application/json": {
                "schema": {
                  "$ref": "#/components/schemas/QueryResponse"
                }
              }
            }
          },
          "422": {
            "description": "Validation Error",
            "content": {
              "application/json": {
                "schema": {
                  "$ref": "#/components/schemas/HTTPValidationError"
                }
              }
            }
          }
        }
      }
    },
    "/api/v1/collections/{collection_name}": {
      "get": {
        "summary": "Get Collection",
        "operationId": "get_collection",
        "parameters": [
          {
            "name": "collection_name",
            "in": "path",
            "required": true,
            "schema": {
              "type": "string",
              "title": "Collection Name"
            }
          },
          {
            "name": "tenant",
            "in": "query",
            "required": false,
            "schema": {
              "type": "string",
              "default": "default_tenant",
              "title": "Tenant"
            }
          },
          {
            "name": "database",
            "in": "query",
            "required": false,
            "schema": {
              "type": "string",
              "default": "default_database",
              "title": "Database"
            }
          }
        ],
        "responses": {
          "200": {
            "description": "Successful Response",
            "content": {
              "application/json": {
                "schema": {
                  "$ref": "#/components/schemas/CollectionType"
                }
              }
            }
          },
          "422": {
            "description": "Validation Error",
            "content": {
              "application/json": {
                "schema": {
                  "$ref": "#/components/schemas/HTTPValidationError"
                }
              }
            }
          }
        }
      },
      "delete": {
        "summary": "Delete Collection",
        "operationId": "delete_collection",
        "parameters": [
          {
            "name": "collection_name",
            "in": "path",
            "required": true,
            "schema": {
              "type": "string",
              "title": "Collection Name"
            }
          },
          {
            "name": "tenant",
            "in": "query",
            "required": false,
            "schema": {
              "type": "string",
              "default": "default_tenant",
              "title": "Tenant"
            }
          },
          {
            "name": "database",
            "in": "query",
            "required": false,
            "schema": {
              "type": "string",
              "default": "default_database",
              "title": "Database"
            }
          }
        ],
        "responses": {
          "200": {
            "description": "Successful Response",
            "content": {
              "application/json": {
                "schema": {}
              }
            }
          },
          "422": {
            "description": "Validation Error",
            "content": {
              "application/json": {
                "schema": {
                  "$ref": "#/components/schemas/HTTPValidationError"
                }
              }
            }
          }
        }
      }
    },
    "/api/v1/collections/{collection_id}": {
      "put": {
        "summary": "Update Collection",
        "operationId": "update_collection",
        "parameters": [
          {
            "name": "collection_id",
            "in": "path",
            "required": true,
            "schema": {
              "type": "string",
              "title": "Collection Id"
            }
          }
        ],
        "requestBody": {
          "required": true,
          "content": {
            "application/json": {
              "schema": {
                "$ref": "#/components/schemas/UpdateCollection"
              }
            }
          }
        },
        "responses": {
          "200": {
            "description": "Successful Response",
            "content": {
              "application/json": {
                "schema": {}
              }
            }
          },
          "422": {
            "description": "Validation Error",
            "content": {
              "application/json": {
                "schema": {
                  "$ref": "#/components/schemas/HTTPValidationError"
                }
              }
            }
          }
        }
      }
    }
  },
  "components": {
    "schemas": {
      "AddEmbedding": {
        "properties": {
          "embeddings": {
            "type": "array",
            "items": {
              "type": "array",
              "items": {
                "type": "number"
              },
              "nullable": true
            },
            "nullable": true,
            "title": "Embeddings",
            "description": "Optional embeddings of the items to add."
          },
          "metadatas": {
            "items": {
              "type": "object",
              "additionalProperties": {
                "type": "object"
              },
              "nullable": true
            },
            "type": "array",
            "nullable": true,
            "title": "Metadatas",
            "description": "Optional metadatas of the items to add."
          },
          "documents": {
            "items": {
              "type": "string",
              "nullable": true
            },
            "type": "array",
            "nullable": true,
            "title": "Documents",
            "description": "Optional documents of the items to add."
          },
          "uris": {
            "items": {
              "type": "string",
              "nullable": true
            },
            "type": "array",
            "nullable": true,
            "title": "Uris",
            "description": "Optional uris of the items to add."
          },
          "ids": {
            "items": {
              "type": "string"
            },
            "type": "array",
            "title": "Ids",
            "description": "IDs of the items to add."
          }
        },
        "type": "object",
        "description": "Request model for add items to collection.",
        "required": [
          "ids"
        ],
        "title": "AddEmbedding"
      },
      "CollectionType": {
        "properties": {
          "name": {
            "title": "Name",
            "description": "Name of the collection.",
            "type": "string"
          },
          "id": {
            "title": "Id",
            "description": "Id of the collection.",
            "type": "string",
            "format": "uuid"
          },
          "metadata": {
            "title": "Metadata",
            "description": "Metadata of the collection.",
            "type": "object",
            "additionalProperties": {
              "type": "object"
            },
            "nullable": true
          }
        },
        "type": "object",
        "required": [
          "name",
          "id"
        ],
        "title": "CollectionType",
        "description": "A collection of items."
      },
      "CreateCollection": {
        "properties": {
          "name": {
            "type": "string",
            "title": "Name",
            "description": "Name of the collection."
          },
          "metadata": {
            "type": "object",
            "additionalProperties": {
              "type": "object"
            },
            "nullable": true,
            "title": "Metadata",
            "description": "Metadata of the collection."
          },
          "get_or_create": {
            "type": "boolean",
            "title": "Get Or Create",
            "description": "If true, will return existing collection if it exists.",
            "default": false
          }
        },
        "type": "object",
        "required": [
          "name"
        ],
        "title": "CreateCollection",
        "description": "Request model for create collection."
      },
      "DatabaseType": {
        "properties": {
          "id": {
            "type": "string",
            "title": "Id",
            "description": "Id of the database."
          },
          "name": {
            "type": "string",
            "title": "Name",
            "description": "Name of the database."
          },
          "tenant": {
            "type": "string",
            "nullable": true,
            "title": "Tenant",
            "description": "Tenant of the database."
          }
        },
        "type": "object",
        "required": [
          "id",
          "name"
        ],
        "title": "DatabaseType",
        "description": "A database."
      },
      "CreateDatabase": {
        "properties": {
          "name": {
            "type": "string",
            "title": "Name",
            "description": "Name of the database."
          }
        },
        "type": "object",
        "required": [
          "name"
        ],
        "title": "CreateDatabase",
        "description": "Request model for create database."
      },
      "TenantType": {
        "properties": {
          "name": {
            "type": "string",
            "title": "Name",
            "description": "Name of the tenant."
          }
        },
        "type": "object",
        "required": [
          "name"
        ],
        "title": "TenantType",
        "description": "A tenant."
      },
      "CreateTenant": {
        "properties": {
          "name": {
            "type": "string",
            "title": "Name",
            "description": "Name of the tenant."
          }
        },
        "type": "object",
        "required": [
          "name"
        ],
        "title": "CreateTenant",
        "description": "Request model for create tenant."
      },
      "DeleteEmbedding": {
        "properties": {
          "ids": {
            "type": "array",
            "items": {
              "type": "string"
            },
            "nullable": true,
            "title": "Ids",
            "description": "Optional IDs of the items to delete."
          },
          "where": {
            "type": "object",
            "additionalProperties": {
              "type": "object"
            },
            "nullable": true,
            "title": "Where",
            "description": "Optional query condition to filter items to delete based on metadata values."
          },
          "where_document": {
            "type": "object",
            "additionalProperties": {
              "type": "object"
            },
            "nullable": true,
            "title": "Where Document",
            "description": "Optional query condition to filter items to delete based on document content."
          }
        },
        "type": "object",
        "title": "DeleteEmbedding",
        "description": "Request model for delete items from collection."
      },
      "GetEmbedding": {
        "properties": {
          "ids": {
            "type": "array",
            "items": {
              "type": "string"
            },
            "nullable": true,
            "title": "Ids",
            "description": "Optional IDs of the items to get."
          },
          "where": {
            "type": "object",
            "additionalProperties": {
              "type": "object"
            },
            "nullable": true,
            "title": "Where",
            "description": "Optional where clause to filter items by."
          },
          "where_document": {
            "type": "object",
            "additionalProperties": {
              "type": "object"
            },
            "nullable": true,
            "title": "Where Document",
            "description": "Optional where clause to filter items by."
          },
          "sort": {
            "type": "string",
            "nullable": true,
            "title": "Sort",
            "description": "Sort items."
          },
          "limit": {
            "type": "integer",
            "nullable": true,
            "title": "Limit",
            "description": "Optional limit on the number of items to get."
          },
          "offset": {
            "type": "integer",
            "nullable": true,
            "title": "Offset",
            "description": "Optional offset on the items to get."
          },
          "include": {
            "items": {
              "type": "string",
              "enum": [
                "documents",
                "embeddings",
                "metadatas",
                "distances",
                "uris",
                "data"
              ]
            },
            "type": "array",
            "title": "Include",
            "description": "Optional list of items to include in the response."
          }
        },
        "type": "object",
        "title": "GetEmbedding",
        "description": "Request model for get items from collection."
      },
      "GetResponse": {
        "title": "GetResponse",
        "description": "Response model for get items from collection.",
        "type": "object",
        "properties": {
          "ids": {
            "title": "Ids",
            "description": "List of ids of the items.",
            "type": "array",
            "items": {
              "type": "string"
            }
          },
          "embeddings": {
            "title": "Embeddings",
            "description": "List of embeddings of the items.",
            "type": "array",
            "items": {
              "type": "array",
              "items": {
                "type": "number"
              }
            }
          },
          "metadatas": {
            "title": "Metadatas",
            "description": "List of metadatas of the items.",
            "type": "array",
            "items": {
              "type": "object",
              "additionalProperties": {
                "type": "object"
              },
              "nullable": true
            }
          },
          "documents": {
            "title": "Documents",
            "description": "List of documents of the items.",
            "type": "array",
            "items": {
              "type": "string",
              "nullable": true
            }
          }
        },
        "required": [
          "ids"
        ]
      },
      "HTTPValidationError": {
        "properties": {
          "detail": {
            "items": {
              "$ref": "#/components/schemas/ValidationError"
            },
            "type": "array",
            "title": "Detail"
          }
        },
        "type": "object",
        "title": "HTTPValidationError"
      },
      "QueryEmbedding": {
        "properties": {
          "where": {
            "type": "object",
            "additionalProperties": {
              "type": "object"
            },
            "nullable": true,
            "title": "Where",
            "description": "Optional query condition to filter results based on metadata values."
          },
          "where_document": {
            "type": "object",
            "additionalProperties": {
              "type": "object"
            },
            "nullable": true,
            "title": "Where Document",
            "description": "Optional query condition to filter results based on document content."
          },
          "query_embeddings": {
            "items": {
              "type": "array",
              "items": {
                "type": "number"
              }
            },
            "type": "array",
            "title": "Query Embeddings",
            "description": "Optional query embeddings to use for the search."
          },
          "n_results": {
            "type": "integer",
            "title": "N Results",
            "description": "Optional number of results to return",
            "default": 10
          },
          "include": {
            "items": {
              "type": "string",
              "enum": [
                "documents",
                "embeddings",
                "metadatas",
                "distances",
                "uris",
                "data"
              ]
            },
            "type": "array",
            "title": "Include",
            "description": "Optional list of items to include in the response."
          }
        },
        "type": "object",
        "required": [
          "query_embeddings"
        ],
        "title": "QueryEmbedding",
        "description": "Request model for query items from collection."
      },
      "QueryResponse": {
        "properties": {
          "embeddings": {
            "type": "array",
            "items": {
              "items": {
                "items": {
                  "type": "number"
                },
                "type": "array"
              },
              "type": "array"
            },
            "title": "Embeddings",
            "description": "List of embeddings of the items."
          },
          "metadatas": {
            "type": "array",
            "items": {
              "items": {
                "type": "object",
                "additionalProperties": {
                  "type": "object"
                },
                "nullable": true
              },
              "type": "array"
            },
            "nullable": true,
            "title": "Metadatas",
            "description": "List of metadatas of the items."
          },
          "documents": {
            "type": "array",
            "items": {
              "items": {
                "type": "string",
                "nullable": true
              },
              "type": "array"
            },
            "nullable": true,
            "title": "Documents",
            "description": "List of documents of the items."
          },
          "data": {
            "type": "array",
            "items": {
              "items": {
                "type": "string",
                "nullable": true
              },
              "type": "array"
            },
            "nullable": true,
            "title": "Data",
            "description": "List of data of the items."
          },
          "uris": {
            "type": "array",
            "items": {
              "items": {
                "type": "string",
                "nullable": true
              },
              "type": "array"
            },
            "nullable": true,
            "title": "Uris",
            "description": "List of uris of the items."
          },
          "ids": {
            "title": "Ids",
            "description": "List of ids of the items.",
            "type": "array",
            "items": {
              "items": {
                "type": "string"
              },
              "type": "array"
            }
          },
          "distances": {
            "type": "array",
            "items": {
              "items": {
                "type": "number"
              },
              "type": "array"
            },
            "title": "Distances",
            "description": "List of distances of the items."
          }
        },
        "type": "object",
        "required": [
          "ids"
        ],
        "title": "QueryResponse",
        "description": "Response model for query items from collection."
      },
      "UpdateCollection": {
        "properties": {
          "new_name": {
            "type": "string",
            "nullable": true,
            "title": "New Name",
            "description": "New name of the collection."
          },
          "new_metadata": {
            "type": "object",
            "additionalProperties": {
              "type": "object"
            },
            "nullable": true,
            "title": "New Metadata",
            "description": "New metadata of the collection."
          }
        },
        "type": "object",
        "title": "UpdateCollection",
        "description": "Request model for update collection."
      },
      "UpdateEmbedding": {
        "properties": {
          "embeddings": {
            "type": "array",
            "items": {
              "type": "array",
              "items": {
                "type": "number"
              },
              "nullable": true
            },
            "nullable": true,
            "title": "Embeddings",
            "description": "Optional embeddings of the items to update."
          },
          "metadatas": {
            "type": "array",
            "items": {
              "type": "object",
              "additionalProperties": {
                "type": "object"
              },
              "nullable": true
            },
            "nullable": true,
            "title": "Metadatas",
            "description": "Optional metadatas of the items to update."
          },
          "documents": {
            "type": "array",
            "items": {
              "type": "string",
              "nullable": true
            },
            "nullable": true,
            "title": "Documents",
            "description": "Optional documents of the items to update."
          },
          "uris": {
            "type": "array",
            "items": {
              "type": "string",
              "nullable": true
            },
            "nullable": true,
            "title": "Uris",
            "description": "Optional uris of the items to update."
          },
          "ids": {
            "items": {
              "type": "string"
            },
            "type": "array",
            "title": "Ids",
            "description": "IDs of the items to update"
          }
        },
        "type": "object",
        "required": [
          "ids"
        ],
        "title": "UpdateEmbedding",
        "description": "Request model for update items in collection."
      },
      "ValidationError": {
        "properties": {
          "loc": {
            "items": {
              "anyOf": [
                {
                  "type": "string"
                },
                {
                  "type": "integer"
                }
              ]
            },
            "type": "array",
            "title": "Location"
          },
          "msg": {
            "type": "string",
            "title": "Message"
          },
          "type": {
            "type": "string",
            "title": "Error Type"
          }
        },
        "type": "object",
        "required": [
          "loc",
          "msg",
          "type"
        ],
        "title": "ValidationError",
        "description": "An error occurred during a request."
      }
    }
  }
}
